MANIFEST.in
README.md
setup.py
django_mp_modal.egg-info/PKG-INFO
django_mp_modal.egg-info/SOURCES.txt
django_mp_modal.egg-info/dependency_links.txt
django_mp_modal.egg-info/top_level.txt
modal/__init__.py
modal/views.py
modal/static/js/Modal.js
modal/templates/modal.html