Metadata-Version: 2.1
Name: django-mp-modal
Version: 1.0.0
Summary: Django run app
Home-page: https://github.com/pmaigutyak/mp-modal
Download-URL: https://github.com/pmaigutyak/mp-modal/archive/1.0.0.tar.gz
Author: Paul Maigutyak
Author-email: pmaigutyak@gmail.com
License: MIT
